carica_cfn_tools/__init__.py
carica_cfn_tools/cli.py
carica_cfn_tools/stack_config.py
carica_cfn_tools/utils.py
carica_cfn_tools/version.py
carica_cfn_tools-1.28.dist-info/LICENSE
carica_cfn_tools-1.28.dist-info/METADATA
carica_cfn_tools-1.28.dist-info/NOTICE
carica_cfn_tools-1.28.dist-info/WHEEL
carica_cfn_tools-1.28.dist-info/entry_points.txt
carica_cfn_tools-1.28.dist-info/top_level.txt
carica_cfn_tools-1.28.dist-info/RECORD
