Metadata-Version: 2.1
Name: carica-cfn-tools
Version: 1.28
Summary: Tools to manage CloudFormation stack configuration
Home-page: https://github.com/caricalabs/carica-cfn-tools
Author: Carica Labs, LLC
Author-email: info@caricalabs.com
License: APL 2.0
Keywords: cloudformation cfn stack template config configuration
Platform: UNKNOWN
Classifier: Development Status :: 5 - Production/Stable
Classifier: Intended Audience :: System Administrators
Classifier: License :: OSI Approved :: Apache Software License
Classifier: Programming Language :: Python :: 3
License-File: LICENSE
License-File: NOTICE
Requires-Dist: boto3 >=1.9.99
Requires-Dist: click ~=8.0
Requires-Dist: cfn-flip ~=1.3.0
Requires-Dist: aws-sam-translator ~=1.42.0
Requires-Dist: jinja2 ~=3.0
Provides-Extra: dev
Requires-Dist: check-manifest ; extra == 'dev'
Provides-Extra: test
